LICENSE
simulert/__init__.py
simulert/alerter.py
simulert/handlers/__init__.py
simulert/handlers/base_handler.py
simulert/handlers/email.py
simulert/handlers/logs.py
simulert/handlers/slack.py
simulert/logger.py
simulert/tests/unit/__init__.py
simulert/tests/unit/conftest.py
simulert/tests/unit/test_alerter.py
simulert/tests/unit/test_handler_email.py
simulert/tests/unit/test_handler_slack.py
simulert-0.2.1.dist-info/LICENSE
simulert-0.2.1.dist-info/WHEEL
simulert-0.2.1.dist-info/METADATA
simulert-0.2.1.dist-info/RECORD
