Metadata-Version: 2.1
Name: simulert
Version: 0.2.1
Summary: A package to provide useful functionality for sending alerts about running simulations.
Home-page: https://github.com/jjminton/simulert
Keywords: simulation,alert,email
Author: Jeremy Minton
Author-email: jeremyminton@gmail.com
Requires-Python: >=3.6,<4.0
Classifier: Operating System :: OS Independent
Classifier: Programming Language :: Python :: 3
Classifier: Programming Language :: Python :: 3.6
Classifier: Programming Language :: Python :: 3.7
Classifier: Programming Language :: Python :: 3.8
Requires-Dist: poetry (>=1.0,<2.0)
Requires-Dist: slackclient (>=2.5,<3.0)
Project-URL: Repository, https://github.com/jjminton/simulert
